zort/__init__.py
zort/fit.py
zort/initialize.py
zort/lightcurve.py
zort/lightcurveFile.py
zort/object.py
zort/parallel.py
zort/photometry.py
zort/plot.py
zort/radec.py
zort/source.py
zort/utils.py
zort/data/ZTF_CCD_Layout.tbl
zort/data/ZTF_Fields.txt
zort-1.8.3.data/scripts/zort-initialize
zort-1.8.3.dist-info/LICENSE
zort-1.8.3.dist-info/METADATA
zort-1.8.3.dist-info/WHEEL
zort-1.8.3.dist-info/top_level.txt
zort-1.8.3.dist-info/RECORD
