Metadata-Version: 2.1
Name: zort
Version: 1.8.3
Summary: Reader for lightcurves from the ZTF Public Data Release
Home-page: https://github.com/MichaelMedford/zort
Author: Michael Medford
Author-email: michaelmedford@berkeley.edu
License: MIT
Download-URL: https://github.com/MichaelMedford/zort/tarball/1.8.3
Project-URL: Lightcurves, https://www.ztf.caltech.edu/page/dr1#12c
Platform: UNKNOWN
Classifier: Intended Audience :: Science/Research
Classifier: Programming Language :: Python :: 3.6
Classifier: License :: OSI Approved :: MIT License
Classifier: Topic :: Scientific/Engineering :: Astronomy
Classifier: Operating System :: POSIX
Classifier: Operating System :: Unix
Classifier: Operating System :: MacOS
Requires-Python: >=3.5
Requires-Dist: tqdm
Requires-Dist: matplotlib
Requires-Dist: numpy
Requires-Dist: scipy
Requires-Dist: shapely
